corticod/__init__.py
corticod/algorithm/__init__.py
corticod/algorithm/codebook.py
corticod/algorithm/cortical_tree.py
corticod/algorithm/tree.py
corticod/utils/README.md
corticod-0.1.2.dist-info/METADATA
corticod-0.1.2.dist-info/WHEEL
corticod-0.1.2.dist-info/dependency_links.txt
corticod-0.1.2.dist-info/top_level.txt
corticod-0.1.2.dist-info/RECORD
