Metadata-Version: 2.2
Name: corticod
Version: 0.1.2
Summary: A biomimetic cortical coding library for audio compression and signal processing.
Home-page: https://github.com/itu-lab/CorticalCodingCodec
Author: Ahmet Emin Ünal
Author-email: aeunal@hotmail.com
Classifier: Programming Language :: Python :: 3
Classifier: License :: OSI Approved :: MIT License
Classifier: Operating System :: OS Independent
Requires-Python: >=3.9
Requires-Dist: numpy>=2.0.2
Requires-Dist: pandas>=2.2.3
Requires-Dist: scikit-learn>=1.6.0
Requires-Dist: scikit-image>=0.24.0
Requires-Dist: soundfile>=0.12.1
Requires-Dist: path
Requires-Dist: torch
Requires-Dist: torchvision
Requires-Dist: torchaudio
Requires-Dist: torchmetrics>=1.6.1
Requires-Dist: scikit-image
Requires-Dist: constriction
Dynamic: author
Dynamic: author-email
Dynamic: classifier
Dynamic: description
Dynamic: description-content-type
Dynamic: home-page
Dynamic: requires-dist
Dynamic: requires-python
Dynamic: summary
